README.md
setup.cfg
setup.py
topiceval/__init__.py
topiceval/__main__.py
topiceval/allparams.py
topiceval/basemodel.py
topiceval/config.py
topiceval/emailextraction.py
topiceval/makewordvecs.py
topiceval/plotter.py
topiceval/stats.py
topiceval/test.py
topiceval/utils.py
topiceval/w2vparams.py
topiceval.egg-info/PKG-INFO
topiceval.egg-info/SOURCES.txt
topiceval.egg-info/dependency_links.txt
topiceval.egg-info/entry_points.txt
topiceval.egg-info/requires.txt
topiceval.egg-info/top_level.txt
topiceval/coherence/__init__.py
topiceval/coherence/semantic.py
topiceval/data/stopwords.npy
topiceval/data/stopwords_extended.npy
topiceval/dictionarylearning/__init__.py
topiceval/dictionarylearning/bcd.py
topiceval/dictionarylearning/sparse_coding.py
topiceval/dictionarylearning/sparse_dictionary.py
topiceval/lda/__init__.py
topiceval/lda/gensimlda.py
topiceval/lda/params.py
topiceval/preprocessing/__init__.py
topiceval/preprocessing/emailsprocess.py
topiceval/preprocessing/emailstructure.py
topiceval/preprocessing/params.py
topiceval/preprocessing/textcleaning.py
topiceval/thresholdedsvd/__init__.py
topiceval/thresholdedsvd/hyperparams.py
topiceval/thresholdedsvd/learnW.py
topiceval/thresholdedsvd/tsvd.py
topiceval/usereval/__init__.py
topiceval/usereval/senddata.py
topiceval/usereval/task_evaluation.py
topiceval/usereval/topicevalGUI.py
topiceval/usereval/topiceval_application.py
topiceval/usereval/resources/bkdimage.jpg
topiceval/usereval/resources/icon.png