Metadata-Version: 1.1
Name: topiceval
Version: 2.3.1.dev1
Summary: Topic Model User Evaluation
Home-page: UNKNOWN
Author: Avikalp Srivastava
Author-email: avikalp22@gmail.com
License: GNU Lesser General Public License v3 (LGPLv3)
Keywords: topic models,evaluation,svd,sparse nmf,lda
Platform: UNKNOWN
Classifier: Development Status :: 1 - Planning
Classifier: Intended Audience :: Science/Research
Classifier: Topic :: Scientific/Engineering :: Information Analysis
Classifier: License :: OSI Approved :: GNU Lesser General Public License v3 (LGPLv3)
Classifier: Programming Language :: Python :: 2.7
Classifier: Programming Language :: Python :: 3.4
Classifier: Programming Language :: Python :: 3.5
